pylunasvg/__init__.py
pylunasvg/__main__.py
pylunasvg/extensions.py
pylunasvg/pylunasvg.pyi
pylunasvg/pylunasvg.pypy37-pp73-darwin.so
pylunasvg-0.0.2.dist-info/LICENSE
pylunasvg-0.0.2.dist-info/METADATA
pylunasvg-0.0.2.dist-info/WHEEL
pylunasvg-0.0.2.dist-info/entry_points.txt
pylunasvg-0.0.2.dist-info/top_level.txt
pylunasvg-0.0.2.dist-info/RECORD
